flet/.DS_Store
flet/__init__.py
flet/flet.py
flet/page.py
flet/publish.py
flet/api/__init__.py
flet/api/manage_client_pushes.py
flet/api/push_add_request.py
flet/api/push_clean_request.py
flet/api/push_go_route_request.py
flet/api/push_page_update_request.py
flet/api/push_remove_request.py
flet/api/push_update_request.py
flet/cli_tools/__init__.py
flet/cli_tools/publish.py
flet/tools/__init__.py
flet/tools/append_assets_to_dist.py
flet/tools/edit_control_props.py
flet/tools/run_event_function.py
flet/tools/setup_web.py
flet/tools/update_control_on_event.py
flet/tools/update_page_info.py
flet/tools/platform_specifics/__init__.py
flet/tools/platform_specifics/get_platform_name.py
flet/tools/platform_specifics/pythonista_webview.py
flet/utils/__init__.py
flet/utils/all_props_posible.py
flet/utils/api_host.py
flet/utils/appbar_coder.py
flet/utils/control_coder.py
flet/utils/get_all_subcontrols.py
flet/utils/get_control_data.py
flet/utils/get_free_port.py
flet/utils/page_posible_props.py
flet/utils/view_coder.py
flet/utils/web_host.py
flet/web/.DS_Store
flet/web/__init__.py
flet/web/development.zip
flet/web/dist.zip
flet_core/__init__.py
flet_core/alert_dialog.py
flet_core/alignment.py
flet_core/animated_switcher.py
flet_core/animation.py
flet_core/app_bar.py
flet_core/audio.py
flet_core/banner.py
flet_core/blur.py
flet_core/border.py
flet_core/border_radius.py
flet_core/bottom_sheet.py
flet_core/buttons.py
flet_core/callable_control.py
flet_core/card.py
flet_core/checkbox.py
flet_core/circle_avatar.py
flet_core/client_storage.py
flet_core/clipboard.py
flet_core/colors.py
flet_core/column.py
flet_core/connection.py
flet_core/constrained_control.py
flet_core/container.py
flet_core/control.py
flet_core/control_event.py
flet_core/datatable.py
flet_core/divider.py
flet_core/drag_target.py
flet_core/draggable.py
flet_core/dropdown.py
flet_core/elevated_button.py
flet_core/embed_json_encoder.py
flet_core/event.py
flet_core/event_handler.py
flet_core/file_picker.py
flet_lite-1.7.5.dist-info/LICENSE
flet_lite-1.7.5.dist-info/METADATA
flet_lite-1.7.5.dist-info/WHEEL
flet_lite-1.7.5.dist-info/top_level.txt
flet_lite-1.7.5.dist-info/RECORD
