Metadata-Version: 2.1
Name: flet-lite
Version: 1.7.5
Summary: A tiny version of flet to work on mobile development
Home-page: https://github.com/SKbarbon/flet_lite
Author: SKbarbon
Classifier: Programming Language :: Python :: 3
Classifier: Operating System :: MacOS :: MacOS X
Classifier: Operating System :: Microsoft :: Windows
License-File: LICENSE
Requires-Dist: flask-cors
Requires-Dist: flask
Requires-Dist: jsonpickle
Requires-Dist: repath
